juba/__init__.py
juba/__version__.py
juba/forwordfitting.py
juba/markov.py
juba/ner.py
juba/similar.py
juba-0.2.1.dist-info/LICENSE
juba-0.2.1.dist-info/METADATA
juba-0.2.1.dist-info/WHEEL
juba-0.2.1.dist-info/top_level.txt
juba-0.2.1.dist-info/zip-safe
juba-0.2.1.dist-info/RECORD
